<Properties StartupConfiguration="{E8D687FC-6408-FAC7-D4E2-86CD5CA11A83}|">
  <MonoDevelop.Ide.Workbench ActiveDocument="Assets/Scripts/Level.cs">
    <Files>
      <File FileName="Assets/Scripts/Player.cs" Line="24" Column="4" />
      <File FileName="Assets/Scripts/Shredder.cs" />
      <File FileName="Assets/Scripts/EnemyPath.cs" />
      <File FileName="Assets/Scripts/WaveConfig.cs" />
      <File FileName="Assets/Scripts/EnemySpawner.cs" />
      <File FileName="Assets/Scripts/Enemy.cs" Line="55" Column="105" />
      <File FileName="Assets/Scripts/BackgroundScroller.cs" />
      <File FileName="Assets/Scripts/Level.cs" Line="18" Column="6" />
    </Files>
  </MonoDevelop.Ide.Workbench>
  <MonoDevelop.Ide.DebuggingService.PinnedWatches />
  <MonoDevelop.Ide.Workspace ActiveConfiguration="Debug" />
  <MonoDevelop.Ide.ItemProperties.Assembly-CSharp PreferredExecutionTarget="605b5378-93f7-45fd-a8e3-0dcb83a5a3fa" />
  <MonoDevelop.Ide.DebuggingService.Breakpoints>
    <BreakpointStore />
  </MonoDevelop.Ide.DebuggingService.Breakpoints>
  <MultiItemStartupConfigurations />
</Properties>